cron_sentry/__init__.py
cron_sentry/runner.py
cron_sentry/version.py
cron_sentry-0.8.0.dist-info/DESCRIPTION.rst
cron_sentry-0.8.0.dist-info/METADATA
cron_sentry-0.8.0.dist-info/RECORD
cron_sentry-0.8.0.dist-info/WHEEL
cron_sentry-0.8.0.dist-info/entry_points.txt
cron_sentry-0.8.0.dist-info/metadata.json
cron_sentry-0.8.0.dist-info/pbr.json
cron_sentry-0.8.0.dist-info/top_level.txt
