Metadata-Version: 2.0
Name: cron-sentry
Version: 0.8.0
Summary: Cron-Sentry is a command-line wrapper that reports unsuccessful runs to Sentry (https://www.getsentry.com)
Home-page: http://github.com/yipit/cron-sentry
Author: Yipit Coders
Author-email: coders@yipit.com
License: MIT
Platform: UNKNOWN
Classifier: Topic :: Utilities
Classifier: Intended Audience :: System Administrators
Classifier: Operating System :: OS Independent
Classifier: License :: OSI Approved :: MIT License
Requires-Dist: raven
